tpg/__init__.py
tpg/__main__.py
tpg/game.py
tpg/popup.py
tpg/py.typed
tpg/renderer.py
tpg/squares.py
tpg/terrain.py
tpg/ui.py
tpg/upgrade.py
tpg/entities/__init__.py
tpg/entities/cannibal.py
tpg/entities/chest.py
tpg/entities/entity.py
tpg/entities/pirate.py
tpg/entities/player.py
tpg/entities/sea_monster.py
tpg/entities/trader.py
tpg/entities/tribe.py
tpg/files/assets/attribution.txt
tpg/files/assets/mining.png
tpg/files/assets/pirate-ship.png
tpg/files/assets/ship.png
tpg/files/assets/treasure-chest.png
tpg-1.0.1.dist-info/licenses/LICENSE
tpg-1.0.1.dist-info/METADATA
tpg-1.0.1.dist-info/WHEEL
tpg-1.0.1.dist-info/top_level.txt
tpg-1.0.1.dist-info/RECORD
