Metadata-Version: 2.4
Name: tpg
Version: 1.0.1
Summary: tpg
Author: fieryhenry
License: GPL-3.0-or-later License
Project-URL: Homepage, https://codeberg.org/fieryhenry/tpg
Project-URL: Repository, https://codeberg.org/fieryhenry/tpg
Project-URL: Issues, https://codeberg.org/fieryhenry/tpg/issues
Project-URL: Changelog, https://codeberg.org/fieryhenry/tpg/raw/branch/main/CHANGELOG.md
Keywords: game,topdown,grid,2d,python
Classifier: Development Status :: 3 - Alpha
Classifier: Topic :: Games/Entertainment
Classifier: Programming Language :: Python :: 3
Classifier: Programming Language :: Python :: 3.9
Classifier: License :: OSI Approved :: GNU General Public License v3 or later (GPLv3+)
Classifier: Operating System :: OS Independent
Requires-Python: >=3.9
License-File: LICENSE
Requires-Dist: PySide6
Dynamic: license-file
